{
  "recentFiles": [
    {
      "basename": "性能优化",
      "path": "00 Index/性能优化.md"
    },
    {
      "basename": "面试题目录",
      "path": "工作台/面试题目录.md"
    },
    {
      "basename": "nextTick",
      "path": "00 Index/nextTick.md"
    },
    {
      "basename": "Vue双向绑定",
      "path": "00 Index/Vue双向绑定.md"
    },
    {
      "basename": "react原理VUE原理",
      "path": "00 Index/react原理VUE原理.md"
    },
    {
      "basename": "面试技术难点",
      "path": "工作台/面试技术难点.md"
    },
    {
      "basename": "babel转译jsx",
      "path": "00 Index/babel转译jsx.md"
    },
    {
      "basename": "物色公司",
      "path": "工作台/物色公司.md"
    },
    {
      "basename": "性能优化面试题",
      "path": "工作台/性能优化面试题.md"
    },
    {
      "basename": "HTTP 1.0 1.1 2.0 HTTPS",
      "path": "00 Index/HTTP 1.0 1.1 2.0 HTTPS.md"
    },
    {
      "basename": "关键字",
      "path": "工作台/前端技术要点/ts要点/关键字.md"
    },
    {
      "basename": "总结",
      "path": "工作台/前端技术要点/ts要点/总结.md"
    },
    {
      "basename": "映射类型",
      "path": "工作台/前端技术要点/ts要点/映射类型.md"
    },
    {
      "basename": "nginx知识要点",
      "path": "工作台/前端技术要点/浏览器知识要点/nginx知识要点.md"
    },
    {
      "basename": "网络安全",
      "path": "工作台/前端技术要点/浏览器知识要点/网络安全.md"
    },
    {
      "basename": "路由",
      "path": "工作台/前端技术要点/浏览器知识要点/路由.md"
    },
    {
      "basename": "mobx浅析",
      "path": "工作台/前端技术要点/组件库浅析/mobx浅析.md"
    },
    {
      "basename": "redux浅析",
      "path": "工作台/前端技术要点/组件库浅析/redux浅析.md"
    },
    {
      "basename": "Ref常见用法",
      "path": "工作台/前端技术要点/react框架/Ref常见用法.md"
    },
    {
      "basename": "react18新特性",
      "path": "工作台/前端技术要点/react框架/react18新特性.md"
    },
    {
      "basename": "hooks讲解",
      "path": "工作台/前端技术要点/react框架/hooks讲解.md"
    },
    {
      "basename": "通熟易懂React Fiber",
      "path": "工作台/前端技术要点/react框架/通熟易懂React Fiber.md"
    },
    {
      "basename": "生命周期详解",
      "path": "工作台/前端技术要点/react框架/生命周期详解.md"
    },
    {
      "basename": "CDN",
      "path": "00 Index/CDN.md"
    },
    {
      "basename": "webpack",
      "path": "工作台/环境搭建/webpack.md"
    },
    {
      "basename": "CICD",
      "path": "CI/CICD.md"
    },
    {
      "basename": "node中间层",
      "path": "00 Index/node中间层.md"
    },
    {
      "basename": "graghQl",
      "path": "00 Index/graghQl.md"
    },
    {
      "basename": "SSR",
      "path": "00 Index/SSR.md"
    },
    {
      "basename": "koa2和express",
      "path": "00 Index/koa2和express.md"
    },
    {
      "basename": "部署流程",
      "path": "00 Index/部署流程.md"
    },
    {
      "basename": "git hooks",
      "path": "00 Index/git hooks.md"
    },
    {
      "basename": "网络请求",
      "path": "工作台/前端技术要点/浏览器知识要点/网络请求.md"
    },
    {
      "basename": "of 和in",
      "path": "00 Index/of 和in.md"
    },
    {
      "basename": "简单请求和复杂请求",
      "path": "00 Index/简单请求和复杂请求.md"
    },
    {
      "basename": "缓存",
      "path": "00 Index/缓存.md"
    },
    {
      "basename": "VUEX",
      "path": "00 Index/VUEX.md"
    },
    {
      "basename": "前端的发展的演变",
      "path": "工作台/前端技术要点/设计模式/前端的发展的演变.md"
    },
    {
      "basename": "HashRouter 和 HistoryRouter",
      "path": "00 Index/HashRouter 和 HistoryRouter.md"
    },
    {
      "basename": "浏览器内核",
      "path": "00 Index/浏览器内核.md"
    },
    {
      "basename": "产品解读",
      "path": "00 Index/产品解读.md"
    },
    {
      "basename": "节流和防抖",
      "path": "00 Index/节流和防抖.md"
    },
    {
      "basename": "常见问题",
      "path": "工作台/前端技术要点/react框架/常见问题.md"
    },
    {
      "basename": "Flex布局",
      "path": "工作台/前端技术要点/css要点/Flex布局.md"
    },
    {
      "basename": "cookie、sessionStorage、localStorage区别",
      "path": "00 Index/cookie、sessionStorage、localStorage区别.md"
    },
    {
      "basename": "in和indexOf和includes和findIndex",
      "path": "00 Index/in和indexOf和includes和findIndex.md"
    },
    {
      "basename": "promise",
      "path": "00 Index/promise.md"
    },
    {
      "basename": "TCP",
      "path": "00 Index/TCP.md"
    },
    {
      "basename": "面向对象编程",
      "path": "00 Index/面向对象编程.md"
    },
    {
      "basename": "深浅拷贝",
      "path": "00 Index/深浅拷贝.md"
    }
  ],
  "omittedPaths": [],
  "maxLength": null
}